django_shpaml-1.3.0.dist-info/DESCRIPTION.rst
django_shpaml-1.3.0.dist-info/METADATA
django_shpaml-1.3.0.dist-info/metadata.json
django_shpaml-1.3.0.dist-info/RECORD
django_shpaml-1.3.0.dist-info/top_level.txt
django_shpaml-1.3.0.dist-info/WHEEL
shpaml/__init__.py
shpaml/loader.py
shpaml/loaders.py
shpaml/models.py
shpaml/shpaml.py
shpaml/utils.py
