Metadata-Version: 2.0
Name: django-shpaml
Version: 1.3.0
Summary: A Django template loader for loading and converting SHPAML markup to HTML
Home-page: http://shpaml.com
Author: James Robert
Author-email: shpaml@jiaaro.com
License: BSD
Keywords: django shpaml
Platform: UNKNOWN
Classifier: License :: OSI Approved :: BSD License
Classifier: Programming Language :: Python
Classifier: Programming Language :: Python :: 2
Classifier: Programming Language :: Python :: 2.6
Classifier: Programming Language :: Python :: 2.7
Classifier: Programming Language :: Python :: 3
Classifier: Programming Language :: Python :: 3.2
Classifier: Programming Language :: Python :: 3.3
Classifier: Environment :: Web Environment
Classifier: Intended Audience :: Developers
Classifier: Operating System :: OS Independent
Classifier: Topic :: Internet :: WWW/HTTP
Classifier: Topic :: Utilities
Requires-Dist: django (>=1.2)
